Metadata-Version: 2.1
Name: fbgem-gpu-cpu
Version: 100.0.5
Summary: fbgem-gpu-cpu of fbgem-gpu-cpu of fbgem-gpu-cpu
Home-page: UNKNOWN
Author: Alon walker
Author-email: alonwalker@facebook.com
License: UNKNOWN
Platform: UNKNOWN
Classifier: Programming Language :: Python :: 3
Classifier: License :: OSI Approved :: MIT License
Classifier: Operating System :: OS Independent
